{
  "meta": {
    "type": "db",
    "canSave": true,
    "canEdit": true,
    "canAdmin": true,
    "canStar": true,
    "canDelete": true,
    "slug": "dual-indexes",
    "url": "/d/c4994f15-e364-46e9-bb7f-b386636b36ab/dual-indexes",
    "expires": "0001-01-01T00:00:00Z",
    "created": "2024-12-22T02:33:13Z",
    "updated": "2024-12-28T15:33:11Z",
    "updatedBy": "admin",
    "createdBy": "admin",
    "version": 2,
    "hasAcl": false,
    "isFolder": false,
    "folderId": 918,
    "folderUid": "be7n97dap7da8a",
    "folderTitle": "GemFireDual",
    "folderUrl": "/dashboards/f/be7n97dap7da8a/gemfiredual",
    "provisioned": false,
    "provisionedExternalId": "",
    "annotationsPermissions": {
      "dashboard": {
        "canAdd": true,
        "canEdit": true,
        "canDelete": true
      },
      "organization": {
        "canAdd": true,
        "canEdit": true,
        "canDelete": true
      }
    }
  },
  "dashboard": {
    "annotations": {
      "list": [
        {
          "builtIn": 1,
          "datasource": {
            "type": "prometheus",
            "uid": "${DataSource}"
          },
          "enable": true,
          "hide": true,
          "iconColor": "rgba(0, 211, 255, 1)",
          "name": "Annotations & Alerts",
          "type": "dashboard"
        }
      ]
    },
    "editable": true,
    "fiscalYearStartMonth": 0,
    "graphTooltip": 0,
    "id": 944,
    "links": [
      {
        "asDropdown": false,
        "icon": "dashboard",
        "includeVars": false,
        "keepTime": true,
        "tags": [],
        "targetBlank": false,
        "title": "Main",
        "tooltip": "",
        "type": "link",
        "url": "/d/ed5d1905-d13d-446a-83d5-3d33d3aadddc/00main?var-DataSource=$DataSource&var-Cluster=$Cluster&${__url_time_range}"
      },
      {
        "asDropdown": true,
        "icon": "external link",
        "includeVars": false,
        "keepTime": true,
        "tags": [
          "gemfire"
        ],
        "targetBlank": false,
        "title": "GemFire",
        "tooltip": "",
        "type": "dashboards",
        "url": ""
      },
      {
        "asDropdown": false,
        "icon": "dashboard",
        "includeVars": false,
        "keepTime": true,
        "tags": [],
        "targetBlank": false,
        "title": "Dual Main",
        "tooltip": "",
        "type": "link",
        "url": "/d/2f6503d9-5b23-4af6-9a87-08f799229df5/00dual-main?var-DataSource=$DataSource&var-Cluster=$Cluster&var-DataSource2=$DataSource2&var-Cluster2=$Cluster2&${__url_time_range}"
      },
      {
        "asDropdown": true,
        "icon": "external link",
        "includeVars": false,
        "keepTime": true,
        "tags": [
          "dual gemfire"
        ],
        "targetBlank": false,
        "title": "Dual GemFire",
        "tooltip": "",
        "type": "dashboards",
        "url": ""
      },
      {
        "asDropdown": false,
        "icon": "dashboard",
        "includeVars": false,
        "keepTime": true,
        "tags": [],
        "targetBlank": false,
        "title": "All Main",
        "tooltip": "",
        "type": "link",
        "url": "/d/5a076038-1d97-4c44-abe7-26020351d90b/00main-all?${__url_time_range}"
      },
      {
        "asDropdown": true,
        "icon": "external link",
        "includeVars": false,
        "keepTime": true,
        "tags": [
          "all gemfire"
        ],
        "targetBlank": false,
        "title": "All GemFire",
        "tooltip": "",
        "type": "dashboards",
        "url": ""
      },
      {
        "asDropdown": false,
        "icon": "dashboard",
        "includeVars": false,
        "keepTime": false,
        "tags": [],
        "targetBlank": false,
        "title": "PadoGrid",
        "tooltip": "About PadoGrid",
        "type": "link",
        "url": "/d/96e45270-7f77-4f87-89f3-1ab707a30808/padogrid${__url_time_range}"
      }
    ],
    "panels": [
      {
        "datasource": {
          "type": "prometheus",
          "uid": "${DataSource}"
        },
        "description": "$Cluster: Creation, last access, and last access times of the locally owned items",
        "fieldConfig": {
          "defaults": {
            "color": {
              "mode": "thresholds"
            },
            "custom": {
              "align": "auto",
              "cellOptions": {
                "type": "auto"
              },
              "inspect": false
            },
            "mappings": [
              {
                "options": {
                  "pattern": "^.*(=)(\\w.*).*\"$",
                  "result": {
                    "index": 0,
                    "text": "$2"
                  }
                },
                "type": "regex"
              }
            ],
            "thresholds": {
              "mode": "absolute",
              "steps": [
                {
                  "color": "green",
                  "value": null
                },
                {
                  "color": "red",
                  "value": 80
                }
              ]
            }
          },
          "overrides": [
            {
              "matcher": {
                "id": "byRegexp",
                "options": "/.*Time/"
              },
              "properties": [
                {
                  "id": "unit",
                  "value": "dateTimeAsIsoNoDateIfToday"
                }
              ]
            },
            {
              "matcher": {
                "id": "byName",
                "options": "Member"
              },
              "properties": [
                {
                  "id": "links",
                  "value": [
                    {
                      "title": "Member Link",
                      "url": "/d/c5932a49-ac31-44d9-95fe-b3eeb7ac974f/member?var-DataSource=$DataSource&var-Cluster=$Cluster&var-Member=${__value.raw}&${__url_time_range}"
                    }
                  ]
                }
              ]
            }
          ]
        },
        "gridPos": {
          "h": 12,
          "w": 12,
          "x": 0,
          "y": 0
        },
        "id": 1,
        "options": {
          "cellHeight": "sm",
          "footer": {
            "countRows": false,
            "fields": "",
            "reducer": [
              "sum"
            ],
            "show": false
          },
          "frameIndex": 1,
          "showHeader": true
        },
        "pluginVersion": "11.3.1",
        "targets": [
          {
            "datasource": {
              "type": "prometheus",
              "uid": "${DataSource}"
            },
            "editorMode": "code",
            "exemplar": false,
            "expr": "com_gemfire_Metrics_creationTime{$ClusterFilterLabel=\"$Cluster\",prefix=\"set\"}",
            "format": "table",
            "instant": true,
            "legendFormat": "{{instance}}",
            "range": false,
            "refId": "Creation Time"
          },
          {
            "datasource": {
              "type": "prometheus",
              "uid": "${DataSource}"
            },
            "editorMode": "code",
            "exemplar": false,
            "expr": "com_gemfire_Metrics_lastUpdateTime{$ClusterFilterLabel=\"$Cluster\",prefix=\"set\"}",
            "format": "table",
            "hide": false,
            "instant": true,
            "legendFormat": "{{instance}}",
            "range": false,
            "refId": "Update Time"
          },
          {
            "datasource": {
              "type": "prometheus",
              "uid": "${DataSource}"
            },
            "editorMode": "code",
            "exemplar": false,
            "expr": "com_gemfire_Metrics_lastAccessTime{$ClusterFilterLabel=\"$Cluster\",prefix=\"set\"}",
            "format": "table",
            "hide": false,
            "instant": true,
            "legendFormat": "{{instance}}",
            "range": false,
            "refId": "Access Time"
          }
        ],
        "title": "Sets: Access Time",
        "transformations": [
          {
            "id": "joinByField",
            "options": {
              "byField": "instance",
              "mode": "outer"
            }
          },
          {
            "id": "filterFieldsByName",
            "options": {
              "include": {
                "pattern": "instance|tag0 1|Value.*"
              }
            }
          },
          {
            "id": "organize",
            "options": {
              "excludeByName": {},
              "indexByName": {},
              "renameByName": {
                "Value #A": "Creation Time",
                "Value #Access Time": "Access Time",
                "Value #C": "",
                "Value #Creation Time": "Creation Time",
                "Value #Update Time": "Update Time",
                "instance": "Member",
                "instance 1": "Member",
                "tag0": "Set",
                "tag0 1": "Set"
              }
            }
          },
          {
            "id": "sortBy",
            "options": {
              "fields": {},
              "sort": [
                {
                  "field": "Member"
                }
              ]
            }
          }
        ],
        "type": "table"
      },
      {
        "datasource": {
          "type": "prometheus",
          "uid": "${DataSource}"
        },
        "description": "$Cluster2: Creation, last access, and last access times of the locally owned items",
        "fieldConfig": {
          "defaults": {
            "color": {
              "mode": "thresholds"
            },
            "custom": {
              "align": "auto",
              "cellOptions": {
                "type": "auto"
              },
              "inspect": false
            },
            "mappings": [
              {
                "options": {
                  "pattern": "^.*(=)(\\w.*).*\"$",
                  "result": {
                    "index": 0,
                    "text": "$2"
                  }
                },
                "type": "regex"
              }
            ],
            "thresholds": {
              "mode": "absolute",
              "steps": [
                {
                  "color": "green",
                  "value": null
                },
                {
                  "color": "red",
                  "value": 80
                }
              ]
            }
          },
          "overrides": [
            {
              "matcher": {
                "id": "byRegexp",
                "options": "/.*Time/"
              },
              "properties": [
                {
                  "id": "unit",
                  "value": "dateTimeAsIsoNoDateIfToday"
                }
              ]
            },
            {
              "matcher": {
                "id": "byName",
                "options": "Member"
              },
              "properties": [
                {
                  "id": "links",
                  "value": [
                    {
                      "title": "Member Link",
                      "url": "/d/c5932a49-ac31-44d9-95fe-b3eeb7ac974f/member?&var-DataSource=$DataSource2&var-Cluster=$Cluster2&var-Member=${__value.raw}&${__url_time_range}"
                    }
                  ]
                }
              ]
            }
          ]
        },
        "gridPos": {
          "h": 12,
          "w": 12,
          "x": 12,
          "y": 0
        },
        "id": 2,
        "options": {
          "cellHeight": "sm",
          "footer": {
            "countRows": false,
            "fields": "",
            "reducer": [
              "sum"
            ],
            "show": false
          },
          "frameIndex": 1,
          "showHeader": true
        },
        "pluginVersion": "11.3.1",
        "targets": [
          {
            "datasource": {
              "type": "prometheus",
              "uid": "${DataSource}"
            },
            "editorMode": "code",
            "exemplar": false,
            "expr": "com_gemfire_Metrics_creationTime{$ClusterFilterLabel=\"$Cluster2\",prefix=\"set\"}",
            "format": "table",
            "instant": true,
            "legendFormat": "{{instance}}",
            "range": false,
            "refId": "Creation Time"
          },
          {
            "datasource": {
              "type": "prometheus",
              "uid": "${DataSource}"
            },
            "editorMode": "code",
            "exemplar": false,
            "expr": "com_gemfire_Metrics_lastUpdateTime{$ClusterFilterLabel=\"$Cluster2\",prefix=\"set\"}",
            "format": "table",
            "hide": false,
            "instant": true,
            "legendFormat": "{{instance}}",
            "range": false,
            "refId": "Update Time"
          },
          {
            "datasource": {
              "type": "prometheus",
              "uid": "${DataSource}"
            },
            "editorMode": "code",
            "exemplar": false,
            "expr": "com_gemfire_Metrics_lastAccessTime{$ClusterFilterLabel=\"$Cluster2\",prefix=\"set\"}",
            "format": "table",
            "hide": false,
            "instant": true,
            "legendFormat": "{{instance}}",
            "range": false,
            "refId": "Access Time"
          }
        ],
        "title": "Sets: Access Time ($Cluster2)",
        "transformations": [
          {
            "id": "joinByField",
            "options": {
              "byField": "instance",
              "mode": "outer"
            }
          },
          {
            "id": "filterFieldsByName",
            "options": {
              "include": {
                "pattern": "instance|tag0 1|Value.*"
              }
            }
          },
          {
            "id": "organize",
            "options": {
              "excludeByName": {},
              "indexByName": {},
              "renameByName": {
                "Value #A": "Creation Time",
                "Value #Access Time": "Access Time",
                "Value #C": "",
                "Value #Creation Time": "Creation Time",
                "Value #Update Time": "Update Time",
                "instance": "Member",
                "instance 1": "Member",
                "tag0": "Set",
                "tag0 1": "Set"
              }
            }
          },
          {
            "id": "sortBy",
            "options": {
              "fields": {},
              "sort": [
                {
                  "field": "Member"
                }
              ]
            }
          }
        ],
        "type": "table"
      }
    ],
    "preload": false,
    "refresh": "5s",
    "schemaVersion": 40,
    "tags": [
      "dual gemfire",
      "compute",
      "lucene"
    ],
    "templating": {
      "list": [
        {
          "hide": 2,
          "name": "ClusterFilterLabel",
          "query": "job",
          "skipUrlSync": true,
          "type": "constant"
        },
        {
          "includeAll": false,
          "label": "Source",
          "name": "DataSource",
          "options": [],
          "query": "prometheus",
          "refresh": 1,
          "regex": "",
          "type": "datasource"
        },
        {
          "current": {
            "text": [
              ""
            ],
            "value": [
              ""
            ]
          },
          "datasource": {
            "type": "prometheus",
            "uid": "${DataSource}"
          },
          "definition": "label_values($ClusterFilterLabel)",
          "includeAll": false,
          "label": "Cluster",
          "name": "Cluster",
          "options": [],
          "query": {
            "qryType": 1,
            "query": "label_values($ClusterFilterLabel)",
            "refId": "PrometheusVariableQueryEditor-VariableQuery"
          },
          "refresh": 1,
          "regex": "",
          "type": "query"
        },
        {
          "includeAll": false,
          "label": "Source2",
          "name": "DataSource2",
          "options": [],
          "query": "prometheus",
          "refresh": 1,
          "regex": "",
          "type": "datasource"
        },
        {
          "current": {
            "text": [
              ""
            ],
            "value": [
              ""
            ]
          },
          "datasource": {
            "type": "prometheus",
            "uid": "${DataSource}"
          },
          "definition": "label_values($ClusterFilterLabel)",
          "includeAll": false,
          "label": "Cluster2",
          "name": "Cluster2",
          "options": [],
          "query": {
            "qryType": 1,
            "query": "label_values($ClusterFilterLabel)",
            "refId": "PrometheusVariableQueryEditor-VariableQuery"
          },
          "refresh": 1,
          "regex": "",
          "type": "query"
        }
      ]
    },
    "time": {
      "from": "now-5m",
      "to": "now"
    },
    "timepicker": {},
    "timezone": "browser",
    "title": "Dual Indexes",
    "uid": "c4994f15-e364-46e9-bb7f-b386636b36ab",
    "version": 2,
    "weekStart": ""
  }
}
