{
  "meta": {
    "type": "db",
    "canSave": true,
    "canEdit": true,
    "canAdmin": true,
    "canStar": true,
    "canDelete": true,
    "slug": "all-partitioned-regions-columns-total-charts",
    "url": "/d/ebf72f09-701d-43bc-9ae3-4742b98ff98a/all-partitioned-regions-columns-total-charts",
    "expires": "0001-01-01T00:00:00Z",
    "created": "2024-12-22T02:33:07Z",
    "updated": "2024-12-28T15:43:12Z",
    "updatedBy": "admin",
    "createdBy": "admin",
    "version": 2,
    "hasAcl": false,
    "isFolder": false,
    "folderId": 884,
    "folderUid": "ee7n97628aj9cb",
    "folderTitle": "GemFireAll",
    "folderUrl": "/dashboards/f/ee7n97628aj9cb/gemfireall",
    "provisioned": false,
    "provisionedExternalId": "",
    "annotationsPermissions": {
      "dashboard": {
        "canAdd": true,
        "canEdit": true,
        "canDelete": true
      },
      "organization": {
        "canAdd": true,
        "canEdit": true,
        "canDelete": true
      }
    }
  },
  "dashboard": {
    "annotations": {
      "list": [
        {
          "builtIn": 1,
          "datasource": {
            "type": "prometheus",
            "uid": "${DataSource}"
          },
          "enable": true,
          "hide": true,
          "iconColor": "rgba(0, 211, 255, 1)",
          "name": "Annotations & Alerts",
          "type": "dashboard"
        }
      ]
    },
    "editable": true,
    "fiscalYearStartMonth": 0,
    "graphTooltip": 0,
    "id": 894,
    "links": [
      {
        "asDropdown": false,
        "icon": "dashboard",
        "includeVars": false,
        "keepTime": true,
        "tags": [],
        "targetBlank": false,
        "title": "Tables",
        "tooltip": "",
        "type": "link",
        "url": "/d/f0c94184-7607-483a-9940-136a0164f7af/all-maps-columns-total?${__url_time_range}"
      },
      {
        "asDropdown": false,
        "icon": "dashboard",
        "includeVars": false,
        "keepTime": true,
        "tags": [],
        "targetBlank": false,
        "title": "Main",
        "tooltip": "",
        "type": "link",
        "url": "/d/ed5d1905-d13d-446a-83d5-3d33d3aadddc/00main?var-DataSource=$DataSource&var-Cluster=$Cluster&${__url_time_range}"
      },
      {
        "asDropdown": true,
        "icon": "external link",
        "includeVars": false,
        "keepTime": true,
        "tags": [
          "gemfire"
        ],
        "targetBlank": false,
        "title": "GemFire",
        "tooltip": "",
        "type": "dashboards",
        "url": ""
      },
      {
        "asDropdown": false,
        "icon": "dashboard",
        "includeVars": false,
        "keepTime": true,
        "tags": [],
        "targetBlank": false,
        "title": "Dual Main",
        "tooltip": "",
        "type": "link",
        "url": "/d/2f6503d9-5b23-4af6-9a87-08f799229df5/00dual-main?var-DataSource=$DataSource&var-Cluster=$Cluster&var-Cluster2=$Cluster2&${__url_time_range}"
      },
      {
        "asDropdown": true,
        "icon": "external link",
        "includeVars": false,
        "keepTime": true,
        "tags": [
          "dual gemfire"
        ],
        "targetBlank": false,
        "title": "Dual GemFire",
        "tooltip": "",
        "type": "dashboards",
        "url": ""
      },
      {
        "asDropdown": false,
        "icon": "dashboard",
        "includeVars": false,
        "keepTime": true,
        "tags": [],
        "targetBlank": false,
        "title": "All Main",
        "tooltip": "",
        "type": "link",
        "url": "/d/5a076038-1d97-4c44-abe7-26020351d90b/00main-all?${__url_time_range}"
      },
      {
        "asDropdown": true,
        "icon": "external link",
        "includeVars": false,
        "keepTime": true,
        "tags": [
          "all gemfire"
        ],
        "targetBlank": false,
        "title": "All GemFire",
        "tooltip": "",
        "type": "dashboards",
        "url": ""
      },
      {
        "asDropdown": false,
        "icon": "dashboard",
        "includeVars": false,
        "keepTime": false,
        "tags": [],
        "targetBlank": false,
        "title": "PadoGrid",
        "tooltip": "About PadoGrid",
        "type": "link",
        "url": "/d/96e45270-7f77-4f87-89f3-1ab707a30808/padogrid${__url_time_range}"
      }
    ],
    "panels": [
      {
        "datasource": {
          "type": "prometheus",
          "uid": "${DataSource}"
        },
        "description": "Number of map entries owned by the member",
        "fieldConfig": {
          "defaults": {
            "color": {
              "mode": "palette-classic"
            },
            "custom": {
              "axisBorderShow": false,
              "axisCenteredZero": false,
              "axisColorMode": "text",
              "axisLabel": "",
              "axisPlacement": "auto",
              "fillOpacity": 80,
              "gradientMode": "none",
              "hideFrom": {
                "legend": false,
                "tooltip": false,
                "viz": false
              },
              "lineWidth": 1,
              "scaleDistribution": {
                "type": "linear"
              },
              "thresholdsStyle": {
                "mode": "off"
              }
            },
            "mappings": [],
            "thresholds": {
              "mode": "absolute",
              "steps": [
                {
                  "color": "green",
                  "value": null
                },
                {
                  "color": "red",
                  "value": 80
                }
              ]
            },
            "unit": "short"
          },
          "overrides": []
        },
        "gridPos": {
          "h": 9,
          "w": 12,
          "x": 0,
          "y": 0
        },
        "id": 26,
        "options": {
          "barRadius": 0,
          "barWidth": 0.97,
          "fullHighlight": false,
          "groupWidth": 0.7,
          "legend": {
            "calcs": [],
            "displayMode": "list",
            "placement": "right",
            "showLegend": true
          },
          "orientation": "auto",
          "showValue": "auto",
          "stacking": "none",
          "tooltip": {
            "mode": "single",
            "sort": "none"
          },
          "xTickLabelRotation": 0,
          "xTickLabelSpacing": 0
        },
        "pluginVersion": "11.3.1",
        "targets": [
          {
            "datasource": {
              "type": "prometheus",
              "uid": "${DataSource}"
            },
            "editorMode": "code",
            "exemplar": false,
            "expr": "com_gemfire_Metrics_ownedEntryCount{$ClusterFilterLabel=~\"($ClusterList)\",prefix=\"map\"}",
            "format": "table",
            "instant": true,
            "legendFormat": "__auto",
            "range": false,
            "refId": "Entries"
          }
        ],
        "title": "Maps: Entries",
        "transformations": [
          {
            "id": "filterFieldsByName",
            "options": {
              "include": {
                "pattern": "$ClusterFilterLabel|tag0|Value"
              }
            }
          },
          {
            "id": "groupBy",
            "options": {
              "fields": {
                "Value": {
                  "aggregations": [
                    "sum"
                  ],
                  "operation": "aggregate"
                },
                "job": {
                  "aggregations": [],
                  "operation": "groupby"
                },
                "tag0": {
                  "aggregations": [],
                  "operation": "groupby"
                }
              }
            }
          },
          {
            "id": "filterByValue",
            "options": {
              "filters": [
                {
                  "config": {
                    "id": "regex",
                    "options": {
                      "value": "__.*"
                    }
                  },
                  "fieldName": "tag0"
                }
              ],
              "match": "any",
              "type": "exclude"
            }
          },
          {
            "id": "sortBy",
            "options": {
              "fields": {},
              "sort": [
                {
                  "field": "tag0"
                }
              ]
            }
          },
          {
            "id": "groupingToMatrix",
            "options": {
              "columnField": "tag0",
              "emptyValue": "null",
              "rowField": "job",
              "valueField": "Value (sum)"
            }
          },
          {
            "id": "renameByRegex",
            "options": {
              "regex": "^(\".*=)(.*)\"",
              "renamePattern": "$2"
            }
          },
          {
            "id": "organize",
            "options": {
              "excludeByName": {},
              "indexByName": {},
              "renameByName": {
                "job\\tag0": "Cluster"
              }
            }
          },
          {
            "id": "sortBy",
            "options": {
              "fields": {},
              "sort": [
                {
                  "field": "Cluster"
                }
              ]
            }
          }
        ],
        "type": "barchart"
      },
      {
        "datasource": {
          "type": "prometheus",
          "uid": "${DataSource}"
        },
        "description": "Number of backup entries held by the member",
        "fieldConfig": {
          "defaults": {
            "color": {
              "mode": "palette-classic"
            },
            "custom": {
              "axisBorderShow": false,
              "axisCenteredZero": false,
              "axisColorMode": "text",
              "axisLabel": "",
              "axisPlacement": "auto",
              "fillOpacity": 80,
              "gradientMode": "none",
              "hideFrom": {
                "legend": false,
                "tooltip": false,
                "viz": false
              },
              "lineWidth": 1,
              "scaleDistribution": {
                "type": "linear"
              },
              "thresholdsStyle": {
                "mode": "off"
              }
            },
            "mappings": [],
            "thresholds": {
              "mode": "absolute",
              "steps": [
                {
                  "color": "green",
                  "value": null
                },
                {
                  "color": "red",
                  "value": 80
                }
              ]
            },
            "unit": "short"
          },
          "overrides": []
        },
        "gridPos": {
          "h": 9,
          "w": 12,
          "x": 12,
          "y": 0
        },
        "id": 39,
        "options": {
          "barRadius": 0,
          "barWidth": 0.97,
          "fullHighlight": false,
          "groupWidth": 0.7,
          "legend": {
            "calcs": [],
            "displayMode": "list",
            "placement": "right",
            "showLegend": true
          },
          "orientation": "auto",
          "showValue": "auto",
          "stacking": "none",
          "tooltip": {
            "mode": "single",
            "sort": "none"
          },
          "xTickLabelRotation": 0,
          "xTickLabelSpacing": 0
        },
        "pluginVersion": "11.3.1",
        "targets": [
          {
            "datasource": {
              "type": "prometheus",
              "uid": "${DataSource}"
            },
            "editorMode": "code",
            "exemplar": false,
            "expr": "com_gemfire_Metrics_backupEntryCount{$ClusterFilterLabel=~\"($ClusterList)\",prefix=\"map\"}",
            "format": "table",
            "instant": true,
            "legendFormat": "__auto",
            "range": false,
            "refId": "Entries"
          }
        ],
        "title": "Maps: Backup Entries",
        "transformations": [
          {
            "id": "filterFieldsByName",
            "options": {
              "include": {
                "pattern": "$ClusterFilterLabel|tag0|Value"
              }
            }
          },
          {
            "id": "groupBy",
            "options": {
              "fields": {
                "Value": {
                  "aggregations": [
                    "sum"
                  ],
                  "operation": "aggregate"
                },
                "job": {
                  "aggregations": [],
                  "operation": "groupby"
                },
                "tag0": {
                  "aggregations": [],
                  "operation": "groupby"
                }
              }
            }
          },
          {
            "id": "filterByValue",
            "options": {
              "filters": [
                {
                  "config": {
                    "id": "regex",
                    "options": {
                      "value": "__.*"
                    }
                  },
                  "fieldName": "tag0"
                }
              ],
              "match": "any",
              "type": "exclude"
            }
          },
          {
            "id": "sortBy",
            "options": {
              "fields": {},
              "sort": [
                {
                  "field": "tag0"
                }
              ]
            }
          },
          {
            "id": "groupingToMatrix",
            "options": {
              "columnField": "tag0",
              "emptyValue": "null",
              "rowField": "job",
              "valueField": "Value (sum)"
            }
          },
          {
            "id": "renameByRegex",
            "options": {
              "regex": "^(\".*=)(.*)\"",
              "renamePattern": "$2"
            }
          },
          {
            "id": "organize",
            "options": {
              "excludeByName": {},
              "indexByName": {},
              "renameByName": {
                "job\\tag0": "Cluster"
              }
            }
          },
          {
            "id": "sortBy",
            "options": {
              "fields": {},
              "sort": [
                {
                  "field": "Cluster"
                }
              ]
            }
          }
        ],
        "type": "barchart"
      },
      {
        "datasource": {
          "type": "prometheus",
          "uid": "${DataSource}"
        },
        "description": "Memory cost of owned map entries on this member",
        "fieldConfig": {
          "defaults": {
            "color": {
              "mode": "palette-classic"
            },
            "custom": {
              "axisBorderShow": false,
              "axisCenteredZero": false,
              "axisColorMode": "text",
              "axisLabel": "",
              "axisPlacement": "auto",
              "fillOpacity": 80,
              "gradientMode": "none",
              "hideFrom": {
                "legend": false,
                "tooltip": false,
                "viz": false
              },
              "lineWidth": 1,
              "scaleDistribution": {
                "type": "linear"
              },
              "thresholdsStyle": {
                "mode": "off"
              }
            },
            "mappings": [],
            "thresholds": {
              "mode": "absolute",
              "steps": [
                {
                  "color": "green",
                  "value": null
                },
                {
                  "color": "red",
                  "value": 80
                }
              ]
            },
            "unit": "bytes"
          },
          "overrides": []
        },
        "gridPos": {
          "h": 9,
          "w": 12,
          "x": 0,
          "y": 9
        },
        "id": 36,
        "options": {
          "barRadius": 0,
          "barWidth": 0.97,
          "fullHighlight": false,
          "groupWidth": 0.7,
          "legend": {
            "calcs": [],
            "displayMode": "list",
            "placement": "right",
            "showLegend": true
          },
          "orientation": "auto",
          "showValue": "auto",
          "stacking": "none",
          "tooltip": {
            "mode": "single",
            "sort": "none"
          },
          "xTickLabelRotation": 0,
          "xTickLabelSpacing": 0
        },
        "pluginVersion": "11.3.1",
        "targets": [
          {
            "datasource": {
              "type": "prometheus",
              "uid": "${DataSource}"
            },
            "editorMode": "code",
            "exemplar": false,
            "expr": "com_gemfire_Metrics_ownedEntryMemoryCost{$ClusterFilterLabel=~\"($ClusterList)\",prefix=\"map\"}",
            "format": "table",
            "instant": true,
            "legendFormat": "__auto",
            "range": false,
            "refId": "Entries"
          }
        ],
        "title": "Maps: Entry Memory",
        "transformations": [
          {
            "id": "filterFieldsByName",
            "options": {
              "include": {
                "pattern": "$ClusterFilterLabel|tag0|Value"
              }
            }
          },
          {
            "id": "groupBy",
            "options": {
              "fields": {
                "Value": {
                  "aggregations": [
                    "sum"
                  ],
                  "operation": "aggregate"
                },
                "job": {
                  "aggregations": [],
                  "operation": "groupby"
                },
                "tag0": {
                  "aggregations": [],
                  "operation": "groupby"
                }
              }
            }
          },
          {
            "id": "filterByValue",
            "options": {
              "filters": [
                {
                  "config": {
                    "id": "regex",
                    "options": {
                      "value": "__.*"
                    }
                  },
                  "fieldName": "tag0"
                }
              ],
              "match": "any",
              "type": "exclude"
            }
          },
          {
            "id": "sortBy",
            "options": {
              "fields": {},
              "sort": [
                {
                  "field": "tag0"
                }
              ]
            }
          },
          {
            "id": "groupingToMatrix",
            "options": {
              "columnField": "tag0",
              "emptyValue": "null",
              "rowField": "job",
              "valueField": "Value (sum)"
            }
          },
          {
            "id": "renameByRegex",
            "options": {
              "regex": "^(\".*=)(.*)\"",
              "renamePattern": "$2"
            }
          },
          {
            "id": "organize",
            "options": {
              "excludeByName": {},
              "indexByName": {},
              "renameByName": {
                "job\\tag0": "Cluster"
              }
            }
          },
          {
            "id": "sortBy",
            "options": {
              "fields": {},
              "sort": [
                {
                  "field": "Cluster"
                }
              ]
            }
          }
        ],
        "type": "barchart"
      },
      {
        "datasource": {
          "type": "prometheus",
          "uid": "${DataSource}"
        },
        "description": "Memory cost of backup map entries on this member",
        "fieldConfig": {
          "defaults": {
            "color": {
              "mode": "palette-classic"
            },
            "custom": {
              "axisBorderShow": false,
              "axisCenteredZero": false,
              "axisColorMode": "text",
              "axisLabel": "",
              "axisPlacement": "auto",
              "fillOpacity": 80,
              "gradientMode": "none",
              "hideFrom": {
                "legend": false,
                "tooltip": false,
                "viz": false
              },
              "lineWidth": 1,
              "scaleDistribution": {
                "type": "linear"
              },
              "thresholdsStyle": {
                "mode": "off"
              }
            },
            "mappings": [],
            "thresholds": {
              "mode": "absolute",
              "steps": [
                {
                  "color": "green",
                  "value": null
                },
                {
                  "color": "red",
                  "value": 80
                }
              ]
            },
            "unit": "bytes"
          },
          "overrides": []
        },
        "gridPos": {
          "h": 9,
          "w": 12,
          "x": 12,
          "y": 9
        },
        "id": 46,
        "options": {
          "barRadius": 0,
          "barWidth": 0.97,
          "fullHighlight": false,
          "groupWidth": 0.7,
          "legend": {
            "calcs": [],
            "displayMode": "list",
            "placement": "right",
            "showLegend": true
          },
          "orientation": "auto",
          "showValue": "auto",
          "stacking": "none",
          "tooltip": {
            "mode": "single",
            "sort": "none"
          },
          "xTickLabelRotation": 0,
          "xTickLabelSpacing": 0
        },
        "pluginVersion": "11.3.1",
        "targets": [
          {
            "datasource": {
              "type": "prometheus",
              "uid": "${DataSource}"
            },
            "editorMode": "code",
            "exemplar": false,
            "expr": "com_gemfire_Metrics_backupEntryMemoryCost{$ClusterFilterLabel=~\"($ClusterList)\",prefix=\"map\"}",
            "format": "table",
            "instant": true,
            "legendFormat": "__auto",
            "range": false,
            "refId": "Entries"
          }
        ],
        "title": "Maps: Backup Memory",
        "transformations": [
          {
            "id": "filterFieldsByName",
            "options": {
              "include": {
                "pattern": "$ClusterFilterLabel|tag0|Value"
              }
            }
          },
          {
            "id": "groupBy",
            "options": {
              "fields": {
                "Value": {
                  "aggregations": [
                    "sum"
                  ],
                  "operation": "aggregate"
                },
                "job": {
                  "aggregations": [],
                  "operation": "groupby"
                },
                "tag0": {
                  "aggregations": [],
                  "operation": "groupby"
                }
              }
            }
          },
          {
            "id": "filterByValue",
            "options": {
              "filters": [
                {
                  "config": {
                    "id": "regex",
                    "options": {
                      "value": "__.*"
                    }
                  },
                  "fieldName": "tag0"
                }
              ],
              "match": "any",
              "type": "exclude"
            }
          },
          {
            "id": "sortBy",
            "options": {
              "fields": {},
              "sort": [
                {
                  "field": "tag0"
                }
              ]
            }
          },
          {
            "id": "groupingToMatrix",
            "options": {
              "columnField": "tag0",
              "emptyValue": "null",
              "rowField": "job",
              "valueField": "Value (sum)"
            }
          },
          {
            "id": "renameByRegex",
            "options": {
              "regex": "^(\".*=)(.*)\"",
              "renamePattern": "$2"
            }
          },
          {
            "id": "organize",
            "options": {
              "excludeByName": {},
              "indexByName": {},
              "renameByName": {
                "job\\tag0": "Cluster"
              }
            }
          },
          {
            "id": "sortBy",
            "options": {
              "fields": {},
              "sort": [
                {
                  "field": "Cluster"
                }
              ]
            }
          }
        ],
        "type": "barchart"
      },
      {
        "datasource": {
          "type": "prometheus",
          "uid": "${DataSource}"
        },
        "description": "Total heap cost of the Merkle trees used",
        "fieldConfig": {
          "defaults": {
            "color": {
              "mode": "palette-classic"
            },
            "custom": {
              "axisBorderShow": false,
              "axisCenteredZero": false,
              "axisColorMode": "text",
              "axisLabel": "",
              "axisPlacement": "auto",
              "fillOpacity": 80,
              "gradientMode": "none",
              "hideFrom": {
                "legend": false,
                "tooltip": false,
                "viz": false
              },
              "lineWidth": 1,
              "scaleDistribution": {
                "type": "linear"
              },
              "thresholdsStyle": {
                "mode": "off"
              }
            },
            "mappings": [],
            "thresholds": {
              "mode": "absolute",
              "steps": [
                {
                  "color": "green",
                  "value": null
                },
                {
                  "color": "red",
                  "value": 80
                }
              ]
            },
            "unit": "bytes"
          },
          "overrides": []
        },
        "gridPos": {
          "h": 9,
          "w": 12,
          "x": 0,
          "y": 18
        },
        "id": 61,
        "options": {
          "barRadius": 0,
          "barWidth": 0.97,
          "fullHighlight": false,
          "groupWidth": 0.7,
          "legend": {
            "calcs": [],
            "displayMode": "list",
            "placement": "right",
            "showLegend": true
          },
          "orientation": "auto",
          "showValue": "auto",
          "stacking": "none",
          "tooltip": {
            "mode": "single",
            "sort": "none"
          },
          "xTickLabelRotation": 0,
          "xTickLabelSpacing": 0
        },
        "pluginVersion": "11.3.1",
        "targets": [
          {
            "datasource": {
              "type": "prometheus",
              "uid": "${DataSource}"
            },
            "editorMode": "code",
            "exemplar": false,
            "expr": "com_gemfire_Metrics_merkleTreesCost{$ClusterFilterLabel=~\"($ClusterList)\",prefix=\"map\"}",
            "format": "table",
            "instant": true,
            "legendFormat": "__auto",
            "range": false,
            "refId": "Entries"
          }
        ],
        "title": "Maps: Merkle Trees Used Heap (WAN)",
        "transformations": [
          {
            "id": "filterFieldsByName",
            "options": {
              "include": {
                "pattern": "$ClusterFilterLabel|tag0|Value"
              }
            }
          },
          {
            "id": "groupBy",
            "options": {
              "fields": {
                "Value": {
                  "aggregations": [
                    "sum"
                  ],
                  "operation": "aggregate"
                },
                "job": {
                  "aggregations": [],
                  "operation": "groupby"
                },
                "tag0": {
                  "aggregations": [],
                  "operation": "groupby"
                }
              }
            }
          },
          {
            "id": "filterByValue",
            "options": {
              "filters": [
                {
                  "config": {
                    "id": "regex",
                    "options": {
                      "value": "__.*"
                    }
                  },
                  "fieldName": "tag0"
                }
              ],
              "match": "any",
              "type": "exclude"
            }
          },
          {
            "id": "sortBy",
            "options": {
              "fields": {},
              "sort": [
                {
                  "field": "tag0"
                }
              ]
            }
          },
          {
            "id": "groupingToMatrix",
            "options": {
              "columnField": "tag0",
              "emptyValue": "null",
              "rowField": "job",
              "valueField": "Value (sum)"
            }
          },
          {
            "id": "renameByRegex",
            "options": {
              "regex": "^(\".*=)(.*)\"",
              "renamePattern": "$2"
            }
          },
          {
            "id": "organize",
            "options": {
              "excludeByName": {},
              "indexByName": {},
              "renameByName": {
                "job\\tag0": "Cluster"
              }
            }
          },
          {
            "id": "sortBy",
            "options": {
              "fields": {},
              "sort": [
                {
                  "field": "Cluster"
                }
              ]
            }
          }
        ],
        "type": "barchart"
      },
      {
        "datasource": {
          "type": "prometheus",
          "uid": "${DataSource}"
        },
        "description": "Local memory cost of the index (for on-heap indexes in OBJECT or BINARY formats, the returned value is just a best-effort approximation and doesn’t indicate a precise on-heap memory usage of the index)",
        "fieldConfig": {
          "defaults": {
            "color": {
              "mode": "palette-classic"
            },
            "custom": {
              "axisBorderShow": false,
              "axisCenteredZero": false,
              "axisColorMode": "text",
              "axisLabel": "",
              "axisPlacement": "auto",
              "fillOpacity": 80,
              "gradientMode": "none",
              "hideFrom": {
                "legend": false,
                "tooltip": false,
                "viz": false
              },
              "lineWidth": 1,
              "scaleDistribution": {
                "type": "linear"
              },
              "thresholdsStyle": {
                "mode": "off"
              }
            },
            "mappings": [],
            "thresholds": {
              "mode": "absolute",
              "steps": [
                {
                  "color": "green",
                  "value": null
                },
                {
                  "color": "red",
                  "value": 80
                }
              ]
            },
            "unit": "bytes"
          },
          "overrides": []
        },
        "gridPos": {
          "h": 9,
          "w": 12,
          "x": 12,
          "y": 18
        },
        "id": 62,
        "options": {
          "barRadius": 0,
          "barWidth": 0.97,
          "fullHighlight": false,
          "groupWidth": 0.7,
          "legend": {
            "calcs": [],
            "displayMode": "list",
            "placement": "right",
            "showLegend": true
          },
          "orientation": "auto",
          "showValue": "auto",
          "stacking": "none",
          "tooltip": {
            "mode": "single",
            "sort": "none"
          },
          "xTickLabelRotation": 0,
          "xTickLabelSpacing": 0
        },
        "pluginVersion": "11.3.1",
        "targets": [
          {
            "datasource": {
              "type": "prometheus",
              "uid": "${DataSource}"
            },
            "editorMode": "code",
            "exemplar": false,
            "expr": "com_gemfire_Metrics_memoryCost{$ClusterFilterLabel=~\"($ClusterList)\",prefix=\"map.index\"}",
            "format": "table",
            "instant": true,
            "legendFormat": "__auto",
            "range": false,
            "refId": "Entries"
          }
        ],
        "title": "Indexes: Memory Cost",
        "transformations": [
          {
            "id": "filterFieldsByName",
            "options": {
              "include": {
                "pattern": "$ClusterFilterLabel|tag1|Value"
              }
            }
          },
          {
            "id": "groupBy",
            "options": {
              "fields": {
                "Value": {
                  "aggregations": [
                    "sum"
                  ],
                  "operation": "aggregate"
                },
                "job": {
                  "aggregations": [],
                  "operation": "groupby"
                },
                "tag0": {
                  "aggregations": [],
                  "operation": "groupby"
                },
                "tag1": {
                  "aggregations": [],
                  "operation": "groupby"
                }
              }
            }
          },
          {
            "id": "filterByValue",
            "options": {
              "filters": [
                {
                  "config": {
                    "id": "regex",
                    "options": {
                      "value": "__.*"
                    }
                  },
                  "fieldName": "tag1"
                }
              ],
              "match": "any",
              "type": "exclude"
            }
          },
          {
            "id": "sortBy",
            "options": {
              "fields": {},
              "sort": [
                {
                  "field": "tag1"
                }
              ]
            }
          },
          {
            "id": "groupingToMatrix",
            "options": {
              "columnField": "tag1",
              "emptyValue": "null",
              "rowField": "job",
              "valueField": "Value (sum)"
            }
          },
          {
            "id": "renameByRegex",
            "options": {
              "regex": "^(\".*=)(.*)\"",
              "renamePattern": "$2"
            }
          },
          {
            "id": "organize",
            "options": {
              "excludeByName": {},
              "indexByName": {},
              "renameByName": {
                "job\\tag0": "Cluster",
                "job\\tag1": "Cluster",
                "nw/customers": ""
              }
            }
          },
          {
            "id": "sortBy",
            "options": {
              "fields": {},
              "sort": [
                {
                  "field": "Cluster"
                }
              ]
            }
          }
        ],
        "type": "barchart"
      },
      {
        "datasource": {
          "type": "prometheus",
          "uid": "${DataSource}"
        },
        "description": "Number of reads of the locally owned entries",
        "fieldConfig": {
          "defaults": {
            "color": {
              "mode": "palette-classic"
            },
            "custom": {
              "axisBorderShow": false,
              "axisCenteredZero": false,
              "axisColorMode": "text",
              "axisLabel": "",
              "axisPlacement": "auto",
              "fillOpacity": 80,
              "gradientMode": "none",
              "hideFrom": {
                "legend": false,
                "tooltip": false,
                "viz": false
              },
              "lineWidth": 1,
              "scaleDistribution": {
                "type": "linear"
              },
              "thresholdsStyle": {
                "mode": "off"
              }
            },
            "mappings": [],
            "thresholds": {
              "mode": "absolute",
              "steps": [
                {
                  "color": "green",
                  "value": null
                },
                {
                  "color": "red",
                  "value": 80
                }
              ]
            },
            "unit": "short"
          },
          "overrides": []
        },
        "gridPos": {
          "h": 9,
          "w": 12,
          "x": 0,
          "y": 27
        },
        "id": 37,
        "options": {
          "barRadius": 0,
          "barWidth": 0.97,
          "fullHighlight": false,
          "groupWidth": 0.7,
          "legend": {
            "calcs": [],
            "displayMode": "list",
            "placement": "right",
            "showLegend": true
          },
          "orientation": "auto",
          "showValue": "auto",
          "stacking": "none",
          "tooltip": {
            "mode": "single",
            "sort": "none"
          },
          "xTickLabelRotation": 0,
          "xTickLabelSpacing": 0
        },
        "pluginVersion": "11.3.1",
        "targets": [
          {
            "datasource": {
              "type": "prometheus",
              "uid": "${DataSource}"
            },
            "editorMode": "code",
            "exemplar": false,
            "expr": "com_gemfire_Metrics_hits{$ClusterFilterLabel=~\"($ClusterList)\",prefix=\"map\"}",
            "format": "table",
            "instant": true,
            "legendFormat": "__auto",
            "range": false,
            "refId": "Entries"
          }
        ],
        "title": "Maps: Hits",
        "transformations": [
          {
            "id": "filterFieldsByName",
            "options": {
              "include": {
                "pattern": "$ClusterFilterLabel|tag0|Value"
              }
            }
          },
          {
            "id": "groupBy",
            "options": {
              "fields": {
                "Value": {
                  "aggregations": [
                    "sum"
                  ],
                  "operation": "aggregate"
                },
                "job": {
                  "aggregations": [],
                  "operation": "groupby"
                },
                "tag0": {
                  "aggregations": [],
                  "operation": "groupby"
                }
              }
            }
          },
          {
            "id": "filterByValue",
            "options": {
              "filters": [
                {
                  "config": {
                    "id": "regex",
                    "options": {
                      "value": "__.*"
                    }
                  },
                  "fieldName": "tag0"
                }
              ],
              "match": "any",
              "type": "exclude"
            }
          },
          {
            "id": "sortBy",
            "options": {
              "fields": {},
              "sort": [
                {
                  "field": "tag0"
                }
              ]
            }
          },
          {
            "id": "groupingToMatrix",
            "options": {
              "columnField": "tag0",
              "emptyValue": "null",
              "rowField": "job",
              "valueField": "Value (sum)"
            }
          },
          {
            "id": "renameByRegex",
            "options": {
              "regex": "^(\".*=)(.*)\"",
              "renamePattern": "$2"
            }
          },
          {
            "id": "organize",
            "options": {
              "excludeByName": {},
              "indexByName": {},
              "renameByName": {
                "job\\tag0": "Cluster"
              }
            }
          },
          {
            "id": "sortBy",
            "options": {
              "fields": {},
              "sort": [
                {
                  "field": "Cluster"
                }
              ]
            }
          }
        ],
        "type": "barchart"
      },
      {
        "datasource": {
          "type": "prometheus",
          "uid": "${DataSource}"
        },
        "description": "Number of local events received on the map",
        "fieldConfig": {
          "defaults": {
            "color": {
              "mode": "palette-classic"
            },
            "custom": {
              "axisBorderShow": false,
              "axisCenteredZero": false,
              "axisColorMode": "text",
              "axisLabel": "",
              "axisPlacement": "auto",
              "fillOpacity": 80,
              "gradientMode": "none",
              "hideFrom": {
                "legend": false,
                "tooltip": false,
                "viz": false
              },
              "lineWidth": 1,
              "scaleDistribution": {
                "type": "linear"
              },
              "thresholdsStyle": {
                "mode": "off"
              }
            },
            "mappings": [],
            "thresholds": {
              "mode": "absolute",
              "steps": [
                {
                  "color": "green",
                  "value": null
                },
                {
                  "color": "red",
                  "value": 80
                }
              ]
            },
            "unit": "short"
          },
          "overrides": []
        },
        "gridPos": {
          "h": 9,
          "w": 12,
          "x": 12,
          "y": 27
        },
        "id": 48,
        "options": {
          "barRadius": 0,
          "barWidth": 0.97,
          "fullHighlight": false,
          "groupWidth": 0.7,
          "legend": {
            "calcs": [],
            "displayMode": "list",
            "placement": "right",
            "showLegend": true
          },
          "orientation": "auto",
          "showValue": "auto",
          "stacking": "none",
          "tooltip": {
            "mode": "single",
            "sort": "none"
          },
          "xTickLabelRotation": 0,
          "xTickLabelSpacing": 0
        },
        "pluginVersion": "11.3.1",
        "targets": [
          {
            "datasource": {
              "type": "prometheus",
              "uid": "${DataSource}"
            },
            "editorMode": "code",
            "exemplar": false,
            "expr": "com_gemfire_Metrics_numberOfEvents{$ClusterFilterLabel=~\"($ClusterList)\",prefix=\"map\"}",
            "format": "table",
            "instant": true,
            "legendFormat": "__auto",
            "range": false,
            "refId": "Entries"
          }
        ],
        "title": "Maps: Events",
        "transformations": [
          {
            "id": "filterFieldsByName",
            "options": {
              "include": {
                "pattern": "$ClusterFilterLabel|tag0|Value"
              }
            }
          },
          {
            "id": "groupBy",
            "options": {
              "fields": {
                "Value": {
                  "aggregations": [
                    "sum"
                  ],
                  "operation": "aggregate"
                },
                "job": {
                  "aggregations": [],
                  "operation": "groupby"
                },
                "tag0": {
                  "aggregations": [],
                  "operation": "groupby"
                }
              }
            }
          },
          {
            "id": "filterByValue",
            "options": {
              "filters": [
                {
                  "config": {
                    "id": "regex",
                    "options": {
                      "value": "__.*"
                    }
                  },
                  "fieldName": "tag0"
                }
              ],
              "match": "any",
              "type": "exclude"
            }
          },
          {
            "id": "sortBy",
            "options": {
              "fields": {},
              "sort": [
                {
                  "field": "tag0"
                }
              ]
            }
          },
          {
            "id": "groupingToMatrix",
            "options": {
              "columnField": "tag0",
              "emptyValue": "null",
              "rowField": "job",
              "valueField": "Value (sum)"
            }
          },
          {
            "id": "renameByRegex",
            "options": {
              "regex": "^(\".*=)(.*)\"",
              "renamePattern": "$2"
            }
          },
          {
            "id": "organize",
            "options": {
              "excludeByName": {},
              "indexByName": {},
              "renameByName": {
                "job\\tag0": "Cluster"
              }
            }
          },
          {
            "id": "sortBy",
            "options": {
              "fields": {},
              "sort": [
                {
                  "field": "Cluster"
                }
              ]
            }
          }
        ],
        "type": "barchart"
      },
      {
        "datasource": {
          "type": "prometheus",
          "uid": "${DataSource}"
        },
        "description": "Number of expirations happened on locally owned entries, backups are not included",
        "fieldConfig": {
          "defaults": {
            "color": {
              "mode": "palette-classic"
            },
            "custom": {
              "axisBorderShow": false,
              "axisCenteredZero": false,
              "axisColorMode": "text",
              "axisLabel": "",
              "axisPlacement": "auto",
              "fillOpacity": 80,
              "gradientMode": "none",
              "hideFrom": {
                "legend": false,
                "tooltip": false,
                "viz": false
              },
              "lineWidth": 1,
              "scaleDistribution": {
                "type": "linear"
              },
              "thresholdsStyle": {
                "mode": "off"
              }
            },
            "mappings": [],
            "thresholds": {
              "mode": "absolute",
              "steps": [
                {
                  "color": "green"
                },
                {
                  "color": "red",
                  "value": 80
                }
              ]
            },
            "unit": "short"
          },
          "overrides": []
        },
        "gridPos": {
          "h": 9,
          "w": 12,
          "x": 0,
          "y": 36
        },
        "id": 38,
        "options": {
          "barRadius": 0,
          "barWidth": 0.97,
          "fullHighlight": false,
          "groupWidth": 0.7,
          "legend": {
            "calcs": [],
            "displayMode": "list",
            "placement": "right",
            "showLegend": true
          },
          "orientation": "auto",
          "showValue": "auto",
          "stacking": "none",
          "tooltip": {
            "mode": "single",
            "sort": "none"
          },
          "xTickLabelRotation": 0,
          "xTickLabelSpacing": 0
        },
        "pluginVersion": "10.2.0",
        "targets": [
          {
            "datasource": {
              "type": "prometheus",
              "uid": "${DataSource}"
            },
            "editorMode": "code",
            "exemplar": false,
            "expr": "com_gemfire_Metrics_expirationCount{$ClusterFilterLabel=~\"($ClusterList)\",prefix=\"map\"}",
            "format": "table",
            "instant": true,
            "legendFormat": "__auto",
            "range": false,
            "refId": "Entries"
          }
        ],
        "title": "Maps: Expirations",
        "transformations": [
          {
            "id": "filterFieldsByName",
            "options": {
              "include": {
                "pattern": "$ClusterFilterLabel|tag0|Value"
              }
            }
          },
          {
            "id": "groupBy",
            "options": {
              "fields": {
                "Value": {
                  "aggregations": [
                    "sum"
                  ],
                  "operation": "aggregate"
                },
                "job": {
                  "aggregations": [],
                  "operation": "groupby"
                },
                "tag0": {
                  "aggregations": [],
                  "operation": "groupby"
                }
              }
            }
          },
          {
            "id": "filterByValue",
            "options": {
              "filters": [
                {
                  "config": {
                    "id": "regex",
                    "options": {
                      "value": "__.*"
                    }
                  },
                  "fieldName": "tag0"
                }
              ],
              "match": "any",
              "type": "exclude"
            }
          },
          {
            "id": "sortBy",
            "options": {
              "fields": {},
              "sort": [
                {
                  "field": "tag0"
                }
              ]
            }
          },
          {
            "id": "groupingToMatrix",
            "options": {
              "columnField": "tag0",
              "emptyValue": "null",
              "rowField": "job",
              "valueField": "Value (sum)"
            }
          },
          {
            "id": "renameByRegex",
            "options": {
              "regex": "^(\".*=)(.*)\"",
              "renamePattern": "$2"
            }
          },
          {
            "id": "organize",
            "options": {
              "excludeByName": {},
              "indexByName": {},
              "renameByName": {
                "job\\tag0": "Cluster"
              }
            }
          },
          {
            "id": "sortBy",
            "options": {
              "fields": {},
              "sort": [
                {
                  "field": "Cluster"
                }
              ]
            }
          }
        ],
        "type": "barchart"
      },
      {
        "datasource": {
          "type": "prometheus",
          "uid": "${DataSource}"
        },
        "description": "Number of evictions happened on locally owned entries, backups are not included",
        "fieldConfig": {
          "defaults": {
            "color": {
              "mode": "palette-classic"
            },
            "custom": {
              "axisBorderShow": false,
              "axisCenteredZero": false,
              "axisColorMode": "text",
              "axisLabel": "",
              "axisPlacement": "auto",
              "fillOpacity": 80,
              "gradientMode": "none",
              "hideFrom": {
                "legend": false,
                "tooltip": false,
                "viz": false
              },
              "lineWidth": 1,
              "scaleDistribution": {
                "type": "linear"
              },
              "thresholdsStyle": {
                "mode": "off"
              }
            },
            "mappings": [],
            "thresholds": {
              "mode": "absolute",
              "steps": [
                {
                  "color": "green"
                },
                {
                  "color": "red",
                  "value": 80
                }
              ]
            },
            "unit": "short"
          },
          "overrides": []
        },
        "gridPos": {
          "h": 9,
          "w": 12,
          "x": 12,
          "y": 36
        },
        "id": 45,
        "options": {
          "barRadius": 0,
          "barWidth": 0.97,
          "fullHighlight": false,
          "groupWidth": 0.7,
          "legend": {
            "calcs": [],
            "displayMode": "list",
            "placement": "right",
            "showLegend": true
          },
          "orientation": "auto",
          "showValue": "auto",
          "stacking": "none",
          "tooltip": {
            "mode": "single",
            "sort": "none"
          },
          "xTickLabelRotation": 0,
          "xTickLabelSpacing": 0
        },
        "pluginVersion": "10.2.0",
        "targets": [
          {
            "datasource": {
              "type": "prometheus",
              "uid": "${DataSource}"
            },
            "editorMode": "code",
            "exemplar": false,
            "expr": "com_gemfire_Metrics_evictionCount{$ClusterFilterLabel=~\"($ClusterList)\",prefix=\"map\"}",
            "format": "table",
            "instant": true,
            "legendFormat": "__auto",
            "range": false,
            "refId": "Entries"
          }
        ],
        "title": "Maps: Evictions",
        "transformations": [
          {
            "id": "filterFieldsByName",
            "options": {
              "include": {
                "pattern": "$ClusterFilterLabel|tag0|Value"
              }
            }
          },
          {
            "id": "groupBy",
            "options": {
              "fields": {
                "Value": {
                  "aggregations": [
                    "sum"
                  ],
                  "operation": "aggregate"
                },
                "job": {
                  "aggregations": [],
                  "operation": "groupby"
                },
                "tag0": {
                  "aggregations": [],
                  "operation": "groupby"
                }
              }
            }
          },
          {
            "id": "filterByValue",
            "options": {
              "filters": [
                {
                  "config": {
                    "id": "regex",
                    "options": {
                      "value": "__.*"
                    }
                  },
                  "fieldName": "tag0"
                }
              ],
              "match": "any",
              "type": "exclude"
            }
          },
          {
            "id": "sortBy",
            "options": {
              "fields": {},
              "sort": [
                {
                  "field": "tag0"
                }
              ]
            }
          },
          {
            "id": "groupingToMatrix",
            "options": {
              "columnField": "tag0",
              "emptyValue": "null",
              "rowField": "job",
              "valueField": "Value (sum)"
            }
          },
          {
            "id": "renameByRegex",
            "options": {
              "regex": "^(\".*=)(.*)\"",
              "renamePattern": "$2"
            }
          },
          {
            "id": "organize",
            "options": {
              "excludeByName": {},
              "indexByName": {},
              "renameByName": {
                "job\\tag0": "Cluster"
              }
            }
          },
          {
            "id": "sortBy",
            "options": {
              "fields": {},
              "sort": [
                {
                  "field": "Cluster"
                }
              ]
            }
          }
        ],
        "type": "barchart"
      },
      {
        "datasource": {
          "type": "prometheus",
          "uid": "${DataSource}"
        },
        "description": "Number of forced evictions happened on locally owned entries, backups are not included",
        "fieldConfig": {
          "defaults": {
            "color": {
              "mode": "palette-classic"
            },
            "custom": {
              "axisBorderShow": false,
              "axisCenteredZero": false,
              "axisColorMode": "text",
              "axisLabel": "",
              "axisPlacement": "auto",
              "fillOpacity": 80,
              "gradientMode": "none",
              "hideFrom": {
                "legend": false,
                "tooltip": false,
                "viz": false
              },
              "lineWidth": 1,
              "scaleDistribution": {
                "type": "linear"
              },
              "thresholdsStyle": {
                "mode": "off"
              }
            },
            "mappings": [],
            "thresholds": {
              "mode": "absolute",
              "steps": [
                {
                  "color": "green"
                },
                {
                  "color": "red",
                  "value": 80
                }
              ]
            },
            "unit": "short"
          },
          "overrides": []
        },
        "gridPos": {
          "h": 9,
          "w": 12,
          "x": 0,
          "y": 45
        },
        "id": 57,
        "options": {
          "barRadius": 0,
          "barWidth": 0.97,
          "fullHighlight": false,
          "groupWidth": 0.7,
          "legend": {
            "calcs": [],
            "displayMode": "list",
            "placement": "right",
            "showLegend": true
          },
          "orientation": "auto",
          "showValue": "auto",
          "stacking": "none",
          "tooltip": {
            "mode": "single",
            "sort": "none"
          },
          "xTickLabelRotation": 0,
          "xTickLabelSpacing": 0
        },
        "pluginVersion": "10.2.0",
        "targets": [
          {
            "datasource": {
              "type": "prometheus",
              "uid": "${DataSource}"
            },
            "editorMode": "code",
            "exemplar": false,
            "expr": "com_gemfire_Metrics_forceEvictedEntryCount{$ClusterFilterLabel=~\"($ClusterList)\",prefix=\"map\"}",
            "format": "table",
            "instant": true,
            "legendFormat": "__auto",
            "range": false,
            "refId": "Entries"
          }
        ],
        "title": "Maps: Force Evicted Entries",
        "transformations": [
          {
            "id": "filterFieldsByName",
            "options": {
              "include": {
                "pattern": "$ClusterFilterLabel|tag0|Value"
              }
            }
          },
          {
            "id": "groupBy",
            "options": {
              "fields": {
                "Value": {
                  "aggregations": [
                    "sum"
                  ],
                  "operation": "aggregate"
                },
                "job": {
                  "aggregations": [],
                  "operation": "groupby"
                },
                "tag0": {
                  "aggregations": [],
                  "operation": "groupby"
                }
              }
            }
          },
          {
            "id": "filterByValue",
            "options": {
              "filters": [
                {
                  "config": {
                    "id": "regex",
                    "options": {
                      "value": "__.*"
                    }
                  },
                  "fieldName": "tag0"
                }
              ],
              "match": "any",
              "type": "exclude"
            }
          },
          {
            "id": "sortBy",
            "options": {
              "fields": {},
              "sort": [
                {
                  "field": "tag0"
                }
              ]
            }
          },
          {
            "id": "groupingToMatrix",
            "options": {
              "columnField": "tag0",
              "emptyValue": "null",
              "rowField": "job",
              "valueField": "Value (sum)"
            }
          },
          {
            "id": "renameByRegex",
            "options": {
              "regex": "^(\".*=)(.*)\"",
              "renamePattern": "$2"
            }
          },
          {
            "id": "organize",
            "options": {
              "excludeByName": {},
              "indexByName": {},
              "renameByName": {
                "job\\tag0": "Cluster"
              }
            }
          },
          {
            "id": "sortBy",
            "options": {
              "fields": {},
              "sort": [
                {
                  "field": "Cluster"
                }
              ]
            }
          }
        ],
        "type": "barchart"
      },
      {
        "datasource": {
          "type": "prometheus",
          "uid": "${DataSource}"
        },
        "description": "Number of queries executed on the map (it may be imprecise for queries involving partition predicates (PartitionPredicate) on the off-heap storage)",
        "fieldConfig": {
          "defaults": {
            "color": {
              "mode": "palette-classic"
            },
            "custom": {
              "axisBorderShow": false,
              "axisCenteredZero": false,
              "axisColorMode": "text",
              "axisLabel": "",
              "axisPlacement": "auto",
              "fillOpacity": 80,
              "gradientMode": "none",
              "hideFrom": {
                "legend": false,
                "tooltip": false,
                "viz": false
              },
              "lineWidth": 1,
              "scaleDistribution": {
                "type": "linear"
              },
              "thresholdsStyle": {
                "mode": "off"
              }
            },
            "mappings": [],
            "thresholds": {
              "mode": "absolute",
              "steps": [
                {
                  "color": "green"
                },
                {
                  "color": "red",
                  "value": 80
                }
              ]
            },
            "unit": "short"
          },
          "overrides": []
        },
        "gridPos": {
          "h": 9,
          "w": 12,
          "x": 12,
          "y": 45
        },
        "id": 58,
        "options": {
          "barRadius": 0,
          "barWidth": 0.97,
          "fullHighlight": false,
          "groupWidth": 0.7,
          "legend": {
            "calcs": [],
            "displayMode": "list",
            "placement": "right",
            "showLegend": true
          },
          "orientation": "auto",
          "showValue": "auto",
          "stacking": "none",
          "tooltip": {
            "mode": "single",
            "sort": "none"
          },
          "xTickLabelRotation": 0,
          "xTickLabelSpacing": 0
        },
        "pluginVersion": "10.2.0",
        "targets": [
          {
            "datasource": {
              "type": "prometheus",
              "uid": "${DataSource}"
            },
            "editorMode": "code",
            "exemplar": false,
            "expr": "com_gemfire_Metrics_queryCount{$ClusterFilterLabel=~\"($ClusterList)\",prefix=\"map\"}",
            "format": "table",
            "instant": true,
            "legendFormat": "__auto",
            "range": false,
            "refId": "Entries"
          }
        ],
        "title": "Maps: Query Count",
        "transformations": [
          {
            "id": "filterFieldsByName",
            "options": {
              "include": {
                "pattern": "$ClusterFilterLabel|tag0|Value"
              }
            }
          },
          {
            "id": "groupBy",
            "options": {
              "fields": {
                "Value": {
                  "aggregations": [
                    "sum"
                  ],
                  "operation": "aggregate"
                },
                "job": {
                  "aggregations": [],
                  "operation": "groupby"
                },
                "tag0": {
                  "aggregations": [],
                  "operation": "groupby"
                }
              }
            }
          },
          {
            "id": "filterByValue",
            "options": {
              "filters": [
                {
                  "config": {
                    "id": "regex",
                    "options": {
                      "value": "__.*"
                    }
                  },
                  "fieldName": "tag0"
                }
              ],
              "match": "any",
              "type": "exclude"
            }
          },
          {
            "id": "sortBy",
            "options": {
              "fields": {},
              "sort": [
                {
                  "field": "tag0"
                }
              ]
            }
          },
          {
            "id": "groupingToMatrix",
            "options": {
              "columnField": "tag0",
              "emptyValue": "null",
              "rowField": "job",
              "valueField": "Value (sum)"
            }
          },
          {
            "id": "renameByRegex",
            "options": {
              "regex": "^(\".*=)(.*)\"",
              "renamePattern": "$2"
            }
          },
          {
            "id": "organize",
            "options": {
              "excludeByName": {},
              "indexByName": {},
              "renameByName": {
                "job\\tag0": "Cluster"
              }
            }
          },
          {
            "id": "sortBy",
            "options": {
              "fields": {},
              "sort": [
                {
                  "field": "Cluster"
                }
              ]
            }
          }
        ],
        "type": "barchart"
      },
      {
        "datasource": {
          "type": "prometheus",
          "uid": "${DataSource}"
        },
        "description": "Total number of indexed local queries performed on the map",
        "fieldConfig": {
          "defaults": {
            "color": {
              "mode": "palette-classic"
            },
            "custom": {
              "axisBorderShow": false,
              "axisCenteredZero": false,
              "axisColorMode": "text",
              "axisLabel": "",
              "axisPlacement": "auto",
              "fillOpacity": 80,
              "gradientMode": "none",
              "hideFrom": {
                "legend": false,
                "tooltip": false,
                "viz": false
              },
              "lineWidth": 1,
              "scaleDistribution": {
                "type": "linear"
              },
              "thresholdsStyle": {
                "mode": "off"
              }
            },
            "mappings": [],
            "thresholds": {
              "mode": "absolute",
              "steps": [
                {
                  "color": "green"
                },
                {
                  "color": "red",
                  "value": 80
                }
              ]
            },
            "unit": "short"
          },
          "overrides": []
        },
        "gridPos": {
          "h": 9,
          "w": 12,
          "x": 0,
          "y": 54
        },
        "id": 59,
        "options": {
          "barRadius": 0,
          "barWidth": 0.97,
          "fullHighlight": false,
          "groupWidth": 0.7,
          "legend": {
            "calcs": [],
            "displayMode": "list",
            "placement": "right",
            "showLegend": true
          },
          "orientation": "auto",
          "showValue": "auto",
          "stacking": "none",
          "tooltip": {
            "mode": "single",
            "sort": "none"
          },
          "xTickLabelRotation": 0,
          "xTickLabelSpacing": 0
        },
        "pluginVersion": "10.2.0",
        "targets": [
          {
            "datasource": {
              "type": "prometheus",
              "uid": "${DataSource}"
            },
            "editorMode": "code",
            "exemplar": false,
            "expr": "com_gemfire_Metrics_indexedQueryCount{$ClusterFilterLabel=~\"($ClusterList)\",prefix=\"map\"}",
            "format": "table",
            "instant": true,
            "legendFormat": "__auto",
            "range": false,
            "refId": "Entries"
          }
        ],
        "title": "Maps: Indexed Query Count",
        "transformations": [
          {
            "id": "filterFieldsByName",
            "options": {
              "include": {
                "pattern": "$ClusterFilterLabel|tag0|Value"
              }
            }
          },
          {
            "id": "groupBy",
            "options": {
              "fields": {
                "Value": {
                  "aggregations": [
                    "sum"
                  ],
                  "operation": "aggregate"
                },
                "job": {
                  "aggregations": [],
                  "operation": "groupby"
                },
                "tag0": {
                  "aggregations": [],
                  "operation": "groupby"
                }
              }
            }
          },
          {
            "id": "filterByValue",
            "options": {
              "filters": [
                {
                  "config": {
                    "id": "regex",
                    "options": {
                      "value": "__.*"
                    }
                  },
                  "fieldName": "tag0"
                }
              ],
              "match": "any",
              "type": "exclude"
            }
          },
          {
            "id": "sortBy",
            "options": {
              "fields": {},
              "sort": [
                {
                  "field": "tag0"
                }
              ]
            }
          },
          {
            "id": "groupingToMatrix",
            "options": {
              "columnField": "tag0",
              "emptyValue": "null",
              "rowField": "job",
              "valueField": "Value (sum)"
            }
          },
          {
            "id": "renameByRegex",
            "options": {
              "regex": "^(\".*=)(.*)\"",
              "renamePattern": "$2"
            }
          },
          {
            "id": "organize",
            "options": {
              "excludeByName": {},
              "indexByName": {},
              "renameByName": {
                "job\\tag0": "Cluster"
              }
            }
          },
          {
            "id": "sortBy",
            "options": {
              "fields": {},
              "sort": [
                {
                  "field": "Cluster"
                }
              ]
            }
          }
        ],
        "type": "barchart"
      },
      {
        "datasource": {
          "type": "prometheus",
          "uid": "${DataSource}"
        },
        "description": "Total number of other operations performed on this member",
        "fieldConfig": {
          "defaults": {
            "color": {
              "mode": "palette-classic"
            },
            "custom": {
              "axisBorderShow": false,
              "axisCenteredZero": false,
              "axisColorMode": "text",
              "axisLabel": "",
              "axisPlacement": "auto",
              "fillOpacity": 80,
              "gradientMode": "none",
              "hideFrom": {
                "legend": false,
                "tooltip": false,
                "viz": false
              },
              "lineWidth": 1,
              "scaleDistribution": {
                "type": "linear"
              },
              "thresholdsStyle": {
                "mode": "off"
              }
            },
            "mappings": [],
            "thresholds": {
              "mode": "absolute",
              "steps": [
                {
                  "color": "green"
                },
                {
                  "color": "red",
                  "value": 80
                }
              ]
            },
            "unit": "short"
          },
          "overrides": []
        },
        "gridPos": {
          "h": 9,
          "w": 12,
          "x": 12,
          "y": 54
        },
        "id": 60,
        "options": {
          "barRadius": 0,
          "barWidth": 0.97,
          "fullHighlight": false,
          "groupWidth": 0.7,
          "legend": {
            "calcs": [],
            "displayMode": "list",
            "placement": "right",
            "showLegend": true
          },
          "orientation": "auto",
          "showValue": "auto",
          "stacking": "none",
          "tooltip": {
            "mode": "single",
            "sort": "none"
          },
          "xTickLabelRotation": 0,
          "xTickLabelSpacing": 0
        },
        "pluginVersion": "10.2.0",
        "targets": [
          {
            "datasource": {
              "type": "prometheus",
              "uid": "${DataSource}"
            },
            "editorMode": "code",
            "exemplar": false,
            "expr": "com_gemfire_Metrics_numberOfOtherOperations{$ClusterFilterLabel=~\"($ClusterList)\",prefix=\"map\"}",
            "format": "table",
            "instant": true,
            "legendFormat": "__auto",
            "range": false,
            "refId": "Entries"
          }
        ],
        "title": "Maps: Other Operations",
        "transformations": [
          {
            "id": "filterFieldsByName",
            "options": {
              "include": {
                "pattern": "$ClusterFilterLabel|tag0|Value"
              }
            }
          },
          {
            "id": "groupBy",
            "options": {
              "fields": {
                "Value": {
                  "aggregations": [
                    "sum"
                  ],
                  "operation": "aggregate"
                },
                "job": {
                  "aggregations": [],
                  "operation": "groupby"
                },
                "tag0": {
                  "aggregations": [],
                  "operation": "groupby"
                }
              }
            }
          },
          {
            "id": "filterByValue",
            "options": {
              "filters": [
                {
                  "config": {
                    "id": "regex",
                    "options": {
                      "value": "__.*"
                    }
                  },
                  "fieldName": "tag0"
                }
              ],
              "match": "any",
              "type": "exclude"
            }
          },
          {
            "id": "sortBy",
            "options": {
              "fields": {},
              "sort": [
                {
                  "field": "tag0"
                }
              ]
            }
          },
          {
            "id": "groupingToMatrix",
            "options": {
              "columnField": "tag0",
              "emptyValue": "null",
              "rowField": "job",
              "valueField": "Value (sum)"
            }
          },
          {
            "id": "renameByRegex",
            "options": {
              "regex": "^(\".*=)(.*)\"",
              "renamePattern": "$2"
            }
          },
          {
            "id": "organize",
            "options": {
              "excludeByName": {},
              "indexByName": {},
              "renameByName": {
                "job\\tag0": "Cluster"
              }
            }
          },
          {
            "id": "sortBy",
            "options": {
              "fields": {},
              "sort": [
                {
                  "field": "Cluster"
                }
              ]
            }
          }
        ],
        "type": "barchart"
      },
      {
        "datasource": {
          "type": "prometheus",
          "uid": "${DataSource}"
        },
        "description": "Number of locked entries that the member owns",
        "fieldConfig": {
          "defaults": {
            "color": {
              "mode": "palette-classic"
            },
            "custom": {
              "axisBorderShow": false,
              "axisCenteredZero": false,
              "axisColorMode": "text",
              "axisLabel": "",
              "axisPlacement": "auto",
              "fillOpacity": 80,
              "gradientMode": "none",
              "hideFrom": {
                "legend": false,
                "tooltip": false,
                "viz": false
              },
              "lineWidth": 1,
              "scaleDistribution": {
                "type": "linear"
              },
              "thresholdsStyle": {
                "mode": "off"
              }
            },
            "mappings": [],
            "thresholds": {
              "mode": "absolute",
              "steps": [
                {
                  "color": "green"
                },
                {
                  "color": "red",
                  "value": 80
                }
              ]
            },
            "unit": "short"
          },
          "overrides": []
        },
        "gridPos": {
          "h": 9,
          "w": 12,
          "x": 0,
          "y": 63
        },
        "id": 44,
        "options": {
          "barRadius": 0,
          "barWidth": 0.97,
          "fullHighlight": false,
          "groupWidth": 0.7,
          "legend": {
            "calcs": [],
            "displayMode": "list",
            "placement": "right",
            "showLegend": true
          },
          "orientation": "auto",
          "showValue": "auto",
          "stacking": "none",
          "tooltip": {
            "mode": "single",
            "sort": "none"
          },
          "xTickLabelRotation": 0,
          "xTickLabelSpacing": 0
        },
        "pluginVersion": "10.2.0",
        "targets": [
          {
            "datasource": {
              "type": "prometheus",
              "uid": "${DataSource}"
            },
            "editorMode": "code",
            "exemplar": false,
            "expr": "com_gemfire_Metrics_lockedEntryCount{$ClusterFilterLabel=~\"($ClusterList)\",prefix=\"map\"}",
            "format": "table",
            "instant": true,
            "legendFormat": "__auto",
            "range": false,
            "refId": "Entries"
          }
        ],
        "title": "Maps: Locked Entries",
        "transformations": [
          {
            "id": "filterFieldsByName",
            "options": {
              "include": {
                "pattern": "$ClusterFilterLabel|tag0|Value"
              }
            }
          },
          {
            "id": "groupBy",
            "options": {
              "fields": {
                "Value": {
                  "aggregations": [
                    "sum"
                  ],
                  "operation": "aggregate"
                },
                "job": {
                  "aggregations": [],
                  "operation": "groupby"
                },
                "tag0": {
                  "aggregations": [],
                  "operation": "groupby"
                }
              }
            }
          },
          {
            "id": "filterByValue",
            "options": {
              "filters": [
                {
                  "config": {
                    "id": "regex",
                    "options": {
                      "value": "__.*"
                    }
                  },
                  "fieldName": "tag0"
                }
              ],
              "match": "any",
              "type": "exclude"
            }
          },
          {
            "id": "sortBy",
            "options": {
              "fields": {},
              "sort": [
                {
                  "field": "tag0"
                }
              ]
            }
          },
          {
            "id": "groupingToMatrix",
            "options": {
              "columnField": "tag0",
              "emptyValue": "null",
              "rowField": "job",
              "valueField": "Value (sum)"
            }
          },
          {
            "id": "renameByRegex",
            "options": {
              "regex": "^(\".*=)(.*)\"",
              "renamePattern": "$2"
            }
          },
          {
            "id": "organize",
            "options": {
              "excludeByName": {},
              "indexByName": {},
              "renameByName": {
                "job\\tag0": "Cluster"
              }
            }
          },
          {
            "id": "sortBy",
            "options": {
              "fields": {},
              "sort": [
                {
                  "field": "Cluster"
                }
              ]
            }
          }
        ],
        "type": "barchart"
      },
      {
        "datasource": {
          "type": "prometheus",
          "uid": "${DataSource}"
        },
        "description": "Number of updated but not persisted yet entries, dirty entries, that the member owns",
        "fieldConfig": {
          "defaults": {
            "color": {
              "mode": "palette-classic"
            },
            "custom": {
              "axisBorderShow": false,
              "axisCenteredZero": false,
              "axisColorMode": "text",
              "axisLabel": "",
              "axisPlacement": "auto",
              "fillOpacity": 80,
              "gradientMode": "none",
              "hideFrom": {
                "legend": false,
                "tooltip": false,
                "viz": false
              },
              "lineWidth": 1,
              "scaleDistribution": {
                "type": "linear"
              },
              "thresholdsStyle": {
                "mode": "off"
              }
            },
            "mappings": [],
            "thresholds": {
              "mode": "absolute",
              "steps": [
                {
                  "color": "green"
                },
                {
                  "color": "red",
                  "value": 80
                }
              ]
            },
            "unit": "short"
          },
          "overrides": []
        },
        "gridPos": {
          "h": 9,
          "w": 12,
          "x": 12,
          "y": 63
        },
        "id": 41,
        "options": {
          "barRadius": 0,
          "barWidth": 0.97,
          "fullHighlight": false,
          "groupWidth": 0.7,
          "legend": {
            "calcs": [],
            "displayMode": "list",
            "placement": "right",
            "showLegend": true
          },
          "orientation": "auto",
          "showValue": "auto",
          "stacking": "none",
          "tooltip": {
            "mode": "single",
            "sort": "none"
          },
          "xTickLabelRotation": 0,
          "xTickLabelSpacing": 0
        },
        "pluginVersion": "10.2.0",
        "targets": [
          {
            "datasource": {
              "type": "prometheus",
              "uid": "${DataSource}"
            },
            "editorMode": "code",
            "exemplar": false,
            "expr": "com_gemfire_Metrics_dirtyEntryCount{$ClusterFilterLabel=~\"($ClusterList)\",prefix=\"map\"}",
            "format": "table",
            "instant": true,
            "legendFormat": "__auto",
            "range": false,
            "refId": "Entries"
          }
        ],
        "title": "Maps: Dirty Entries",
        "transformations": [
          {
            "id": "filterFieldsByName",
            "options": {
              "include": {
                "pattern": "$ClusterFilterLabel|tag0|Value"
              }
            }
          },
          {
            "id": "groupBy",
            "options": {
              "fields": {
                "Value": {
                  "aggregations": [
                    "sum"
                  ],
                  "operation": "aggregate"
                },
                "job": {
                  "aggregations": [],
                  "operation": "groupby"
                },
                "tag0": {
                  "aggregations": [],
                  "operation": "groupby"
                }
              }
            }
          },
          {
            "id": "filterByValue",
            "options": {
              "filters": [
                {
                  "config": {
                    "id": "regex",
                    "options": {
                      "value": "__.*"
                    }
                  },
                  "fieldName": "tag0"
                }
              ],
              "match": "any",
              "type": "exclude"
            }
          },
          {
            "id": "sortBy",
            "options": {
              "fields": {},
              "sort": [
                {
                  "field": "tag0"
                }
              ]
            }
          },
          {
            "id": "groupingToMatrix",
            "options": {
              "columnField": "tag0",
              "emptyValue": "null",
              "rowField": "job",
              "valueField": "Value (sum)"
            }
          },
          {
            "id": "renameByRegex",
            "options": {
              "regex": "^(\".*=)(.*)\"",
              "renamePattern": "$2"
            }
          },
          {
            "id": "organize",
            "options": {
              "excludeByName": {},
              "indexByName": {},
              "renameByName": {
                "job\\tag0": "Cluster"
              }
            }
          },
          {
            "id": "sortBy",
            "options": {
              "fields": {},
              "sort": [
                {
                  "field": "Cluster"
                }
              ]
            }
          }
        ],
        "type": "barchart"
      },
      {
        "datasource": {
          "type": "prometheus",
          "uid": "${DataSource}"
        },
        "description": "Number of off loaded map store operations waiting to be processed",
        "fieldConfig": {
          "defaults": {
            "color": {
              "mode": "palette-classic"
            },
            "custom": {
              "axisBorderShow": false,
              "axisCenteredZero": false,
              "axisColorMode": "text",
              "axisLabel": "",
              "axisPlacement": "auto",
              "fillOpacity": 80,
              "gradientMode": "none",
              "hideFrom": {
                "legend": false,
                "tooltip": false,
                "viz": false
              },
              "lineWidth": 1,
              "scaleDistribution": {
                "type": "linear"
              },
              "thresholdsStyle": {
                "mode": "off"
              }
            },
            "mappings": [],
            "thresholds": {
              "mode": "absolute",
              "steps": [
                {
                  "color": "green"
                },
                {
                  "color": "red",
                  "value": 80
                }
              ]
            },
            "unit": "short"
          },
          "overrides": []
        },
        "gridPos": {
          "h": 9,
          "w": 12,
          "x": 0,
          "y": 72
        },
        "id": 56,
        "options": {
          "barRadius": 0,
          "barWidth": 0.97,
          "fullHighlight": false,
          "groupWidth": 0.7,
          "legend": {
            "calcs": [],
            "displayMode": "list",
            "placement": "right",
            "showLegend": true
          },
          "orientation": "auto",
          "showValue": "auto",
          "stacking": "none",
          "tooltip": {
            "mode": "single",
            "sort": "none"
          },
          "xTickLabelRotation": 0,
          "xTickLabelSpacing": 0
        },
        "pluginVersion": "10.2.0",
        "targets": [
          {
            "datasource": {
              "type": "prometheus",
              "uid": "${DataSource}"
            },
            "editorMode": "code",
            "exemplar": false,
            "expr": "com_gemfire_Metrics_waitingToBeProcessedCount{$ClusterFilterLabel=~\"$ClusterList\",prefix=\"map.store.offloaded.operations\"}",
            "format": "table",
            "instant": true,
            "legendFormat": "__auto",
            "range": false,
            "refId": "Entries"
          }
        ],
        "title": "Map Store: Waiting To Be Processed Count",
        "transformations": [
          {
            "id": "filterFieldsByName",
            "options": {
              "include": {
                "pattern": "$ClusterFilterLabel|tag0|Value"
              }
            }
          },
          {
            "id": "groupBy",
            "options": {
              "fields": {
                "Value": {
                  "aggregations": [
                    "sum"
                  ],
                  "operation": "aggregate"
                },
                "job": {
                  "aggregations": [],
                  "operation": "groupby"
                },
                "tag0": {
                  "aggregations": [],
                  "operation": "groupby"
                }
              }
            }
          },
          {
            "id": "filterByValue",
            "options": {
              "filters": [
                {
                  "config": {
                    "id": "regex",
                    "options": {
                      "value": "__.*"
                    }
                  },
                  "fieldName": "tag0"
                }
              ],
              "match": "any",
              "type": "exclude"
            }
          },
          {
            "id": "sortBy",
            "options": {
              "fields": {},
              "sort": [
                {
                  "field": "tag0"
                }
              ]
            }
          },
          {
            "id": "groupingToMatrix",
            "options": {
              "columnField": "tag0",
              "emptyValue": "null",
              "rowField": "job",
              "valueField": "Value (sum)"
            }
          },
          {
            "id": "renameByRegex",
            "options": {
              "regex": "^(\".*=)(.*)\"",
              "renamePattern": "$2"
            }
          },
          {
            "id": "organize",
            "options": {
              "excludeByName": {},
              "indexByName": {},
              "renameByName": {
                "job\\tag0": "Cluster"
              }
            }
          },
          {
            "id": "sortBy",
            "options": {
              "fields": {},
              "sort": [
                {
                  "field": "Cluster"
                }
              ]
            }
          }
        ],
        "type": "barchart"
      }
    ],
    "preload": false,
    "refresh": "5s",
    "schemaVersion": 40,
    "tags": [
      "all gemfire",
      "partitioned region",
      "storage"
    ],
    "templating": {
      "list": [
        {
          "hide": 2,
          "name": "ClusterFilterLabel",
          "query": "job",
          "skipUrlSync": true,
          "type": "constant"
        },
        {
          "includeAll": false,
          "label": "Source",
          "name": "DataSource",
          "options": [],
          "query": "prometheus",
          "refresh": 1,
          "regex": "",
          "type": "datasource"
        },
        {
          "current": {
            "text": [
              ""
            ],
            "value": [
              ""
            ]
          },
          "datasource": {
            "type": "prometheus",
            "uid": "${DataSource}"
          },
          "definition": "label_values($ClusterFilterLabel)",
          "hide": 2,
          "includeAll": false,
          "label": "Cluster",
          "name": "Cluster",
          "options": [],
          "query": {
            "qryType": 1,
            "query": "label_values($ClusterFilterLabel)",
            "refId": "PrometheusVariableQueryEditor-VariableQuery"
          },
          "refresh": 1,
          "regex": "",
          "type": "query"
        },
        {
          "hide": 2,
          "includeAll": false,
          "label": "Source2",
          "name": "DataSource2",
          "options": [],
          "query": "prometheus",
          "refresh": 1,
          "regex": "",
          "type": "datasource"
        },
        {
          "current": {
            "text": [
              ""
            ],
            "value": [
              ""
            ]
          },
          "datasource": {
            "type": "prometheus",
            "uid": "${DataSource}"
          },
          "definition": "label_values($ClusterFilterLabel)",
          "hide": 2,
          "includeAll": false,
          "label": "Cluster2",
          "name": "Cluster2",
          "options": [],
          "query": {
            "qryType": 1,
            "query": "label_values($ClusterFilterLabel)",
            "refId": "PrometheusVariableQueryEditor-VariableQuery"
          },
          "refresh": 1,
          "regex": "",
          "type": "query"
        },
        {
          "current": {
            "text": [
              "All"
            ],
            "value": [
              ""
            ]
          },
          "datasource": {
            "type": "prometheus",
            "uid": "${DataSource}"
          },
          "definition": "label_values($ClusterFilterLabel)",
          "includeAll": true,
          "label": "Clusters",
          "multi": true,
          "name": "ClusterList",
          "options": [],
          "query": {
            "qryType": 1,
            "query": "label_values($ClusterFilterLabel)",
            "refId": "PrometheusVariableQueryEditor-VariableQuery"
          },
          "refresh": 1,
          "regex": "",
          "type": "query"
        },
        {
          "description": "",
          "hide": 2,
          "label": "Cluster 3",
          "name": "Cluster3",
          "query": "wan1",
          "skipUrlSync": true,
          "type": "constant"
        },
        {
          "description": "",
          "hide": 2,
          "label": "Cluster 4",
          "name": "Cluster4",
          "query": "wan2",
          "skipUrlSync": true,
          "type": "constant"
        }
      ]
    },
    "time": {
      "from": "now-5m",
      "to": "now"
    },
    "timepicker": {},
    "timezone": "browser",
    "title": "All Partitioned Regions Columns Total Charts",
    "uid": "ebf72f09-701d-43bc-9ae3-4742b98ff98a",
    "version": 2,
    "weekStart": ""
  }
}
